LICENSE
zapi/__init__.py
zapi/mdp/__init__.py
zapi/mdp/client.py
zapi/mdp/constant.py
zapi/mdp/util.py
zapi/mdp/worker.py
py_zapi-0.1.2.dist-info/LICENSE
py_zapi-0.1.2.dist-info/WHEEL
py_zapi-0.1.2.dist-info/METADATA
py_zapi-0.1.2.dist-info/RECORD
